Metadata-Version: 2.1
Name: is-palindrome
Version: 0.0.1
Summary: A python module for checking palindrome property in a string 
Home-page: https://github.com/pavanchikkanna/is_palindrome
Author: Pavan R
Author-email: pavanravikumar1998@gmail.com
License: MIT
Platform: UNKNOWN
Classifier: Programming Language :: Python :: 3
Classifier: License :: OSI Approved :: MIT License
Classifier: Operating System :: OS Independent
Requires-Python: >=3.6
